quillsql/__init__.py
quillsql/core.py
quillsql/error.py
quillsql/assets/__init__.py
quillsql/assets/pgtypes.py
quillsql/db/__init__.py
quillsql/db/bigquery.py
quillsql/db/cached_connection.py
quillsql/db/db_helper.py
quillsql/db/postgres.py
quillsql/utils/__init__.py
quillsql/utils/filters.py
quillsql/utils/pivot_template.py
quillsql/utils/post_quill_executor.py
quillsql/utils/run_query_processes.py
quillsql/utils/schema_conversion.py
quillsql/utils/tenants.py
quillsql-2.2.8.dist-info/METADATA
quillsql-2.2.8.dist-info/WHEEL
quillsql-2.2.8.dist-info/top_level.txt
quillsql-2.2.8.dist-info/RECORD
