Metadata-Version: 2.4
Name: quillsql
Version: 2.2.8
Summary: Quill SDK for Python.
Home-page: https://github.com/quill-sql/quill-python
Author: Quill
Author-email: shawn@quill.co
Requires-Dist: psycopg2-binary
Requires-Dist: requests
Requires-Dist: redis
Requires-Dist: python-dotenv
Requires-Dist: pytest
Requires-Dist: google-cloud-bigquery
Requires-Dist: google-auth
Dynamic: author
Dynamic: author-email
Dynamic: description
Dynamic: description-content-type
Dynamic: home-page
Dynamic: requires-dist
Dynamic: summary
